dclick/__init__.py
dclick/command.py
dclick/decorators.py
dclick-0.1.3.dist-info/AUTHORS.rst
dclick-0.1.3.dist-info/LICENSE
dclick-0.1.3.dist-info/METADATA
dclick-0.1.3.dist-info/WHEEL
dclick-0.1.3.dist-info/entry_points.txt
dclick-0.1.3.dist-info/top_level.txt
dclick-0.1.3.dist-info/RECORD
