Metadata-Version: 2.1
Name: dclick
Version: 0.1.3
Summary: Extend click functionnalities by allowing parameters to be passed in a config file
Home-page: https://github.com/anottergithubuser/double_click
Author: Thomas PESNEAU
Author-email: thomaspesneau@gmail.com
License: BSD license
Keywords: dclick
Platform: UNKNOWN
Classifier: Development Status :: 2 - Pre-Alpha
Classifier: Intended Audience :: Developers
Classifier: License :: OSI Approved :: BSD License
Classifier: Natural Language :: English
Classifier: Programming Language :: Python :: 3
Classifier: Programming Language :: Python :: 3.5
Classifier: Programming Language :: Python :: 3.6
Classifier: Programming Language :: Python :: 3.7
Classifier: Programming Language :: Python :: 3.8
Requires-Python: >=3.5
Requires-Dist: Click (>=7.0)
